django_tomselect2/__init__.py
django_tomselect2/_version.py
django_tomselect2/apps.py
django_tomselect2/cache.py
django_tomselect2/conf.py
django_tomselect2/forms.py
django_tomselect2/urls.py
django_tomselect2/views.py
django_tomselect2/static/django_tomselect2/django_tomselect.js
django_tomselect2/static/tom-select/LICENSE
django_tomselect2/static/tom-select/css/tom-select.bootstrap4.min.css
django_tomselect2/static/tom-select/css/tom-select.bootstrap5.min.css
django_tomselect2/static/tom-select/css/tom-select.default.min.css
django_tomselect2/static/tom-select/css/tom-select.min.css
django_tomselect2/static/tom-select/js/tom-select.complete.min.js
django_tomselect2-0.1.4.dist-info/METADATA
django_tomselect2-0.1.4.dist-info/WHEEL
django_tomselect2-0.1.4.dist-info/licenses/LICENSE
django_tomselect2-0.1.4.dist-info/RECORD
